README.md
setup.py
onetrigger/__init__.py
onetrigger/configparser.py
onetrigger/oneproviderclient.py
onetrigger/onetrigger.py
onetrigger/version.py
onetrigger.egg-info/PKG-INFO
onetrigger.egg-info/SOURCES.txt
onetrigger.egg-info/dependency_links.txt
onetrigger.egg-info/entry_points.txt
onetrigger.egg-info/not-zip-safe
onetrigger.egg-info/requires.txt
onetrigger.egg-info/top_level.txt