Metadata-Version: 2.1
Name: onetrigger
Version: 1.0.4
Summary: Trigger webhooks by Onedata events
Home-page: https://github.com/grycap/onetrigger
Author: GRyCAP - Universitat Politecnica de Valencia
Author-email: serisgal@i3m.upv.es
License: Apache 2.0
Platform: UNKNOWN
Classifier: Programming Language :: Python :: 3
Classifier: License :: OSI Approved :: Apache Software License
Classifier: Environment :: Console
